ohmytmp/__constant.py
ohmytmp/__core.py
ohmytmp/__init__.py
ohmytmp/__plugin.py
ohmytmp/__predict.py
ohmytmp/plugin.py
ohmytmp-0.0.8.dist-info/LICENSE
ohmytmp-0.0.8.dist-info/METADATA
ohmytmp-0.0.8.dist-info/WHEEL
ohmytmp-0.0.8.dist-info/top_level.txt
ohmytmp-0.0.8.dist-info/RECORD
