Metadata-Version: 2.1
Name: ohmytmp
Version: 0.0.8
Summary: ohmytmp-core
Author-email: userElaina <userelaina@pm.me>
Maintainer-email: userElaina <userelaina@pm.me>
License: MIT License
Project-URL: Homepage, https://github.com/ohmytmp/core
Project-URL: Bug Reports, https://github.com/ohmytmp/core/issues
Project-URL: Source, https://github.com/ohmytmp/core
Keywords: file
Classifier: License :: OSI Approved :: MIT License
Classifier: Programming Language :: Python :: 3
Requires-Python: >=3.7
License-File: LICENSE
